polf.cpython-36m-darwin.so
polf-0.0.12.dist-info/LICENSE
polf-0.0.12.dist-info/METADATA
polf-0.0.12.dist-info/WHEEL
polf-0.0.12.dist-info/top_level.txt
polf-0.0.12.dist-info/RECORD
