Metadata-Version: 2.1
Name: polf
Version: 0.0.12
Summary: Calculate points on lines.
Home-page: UNKNOWN
License: BSD License
Platform: UNKNOWN
Classifier: License :: OSI Approved :: BSD License
Classifier: Operating System :: OS Independent
Classifier: Development Status :: 4 - Beta
Classifier: Programming Language :: Python
Classifier: Programming Language :: Python :: 3.6
Classifier: Programming Language :: Python :: 3.7
Classifier: Programming Language :: Python :: 3.8
Classifier: Programming Language :: Python :: Implementation :: CPython
Classifier: Topic :: Scientific/Engineering :: Mathematics
Classifier: Topic :: Scientific/Engineering :: Image Processing
Classifier: Topic :: Multimedia :: Graphics
Classifier: Intended Audience :: Developers
Classifier: Intended Audience :: Education
Requires-Python: >=3.6
Provides-Extra: dev
Provides-Extra: test
Provides-Extra: doc
